<?xml version="1.0" encoding="utf-8"?>
<Document>
  <Engineering version="V17" />
  <DocumentInfo>
    <Created>2024-06-14T09:52:43.5267752Z</Created>
    <ExportSetting>WithDefaults</ExportSetting>
    <InstalledProducts>
      <Product>
        <DisplayName>Totally Integrated Automation Portal</DisplayName>
        <DisplayVersion>V17</DisplayVersion>
      </Product>
      <OptionPackage>
        <DisplayName>TIA Portal Openness</DisplayName>
        <DisplayVersion>V17</DisplayVersion>
      </OptionPackage>
      <OptionPackage>
        <DisplayName>TIA Portal Version Control Interface</DisplayName>
        <DisplayVersion>V17</DisplayVersion>
      </OptionPackage>
      <OptionPackage>
        <DisplayName>Simotion SCOUT TIA</DisplayName>
        <DisplayVersion>5.4.3.0</DisplayVersion>
      </OptionPackage>
      <Product>
        <DisplayName>SINAMICS Startdrive Advanced</DisplayName>
        <DisplayVersion>V17 SP1 Update 1</DisplayVersion>
      </Product>
      <OptionPackage>
        <DisplayName>SINAMICS Startdrive G110M, G120, G120C, G120D, G120P, G115D</DisplayName>
        <DisplayVersion>V17 SP1 Update 1</DisplayVersion>
      </OptionPackage>
      <OptionPackage>
        <DisplayName>SINAMICS Startdrive G130, G150, S120, S150, SINAMICS MV, S210</DisplayName>
        <DisplayVersion>V17 SP1 Update 1</DisplayVersion>
      </OptionPackage>
      <Product>
        <DisplayName>STEP 7 Professional</DisplayName>
        <DisplayVersion>V17</DisplayVersion>
      </Product>
      <OptionPackage>
        <DisplayName>STEP 7 Safety</DisplayName>
        <DisplayVersion>V17</DisplayVersion>
      </OptionPackage>
      <Product>
        <DisplayName>WinCC Professional</DisplayName>
        <DisplayVersion>V17</DisplayVersion>
      </Product>
    </InstalledProducts>
  </DocumentInfo>
  <SW.Blocks.GlobalDB ID="0">
    <AttributeList>
      <AutoNumber>false</AutoNumber>
      <DBAccessibleFromOPCUA>true</DBAccessibleFromOPCUA>
      <HeaderAuthor />
      <HeaderFamily />
      <HeaderName />
      <HeaderVersion>0.1</HeaderVersion>
      <Interface><Sections xmlns="http://www.siemens.com/automation/Openness/SW/Interface/v5">
  <Section Name="Static">
    <Member Name="TCP_Data_Station4" Datatype="Array[1..6] of &quot;Mod_TCP_Data&quot;" Remanence="Retain" Accessibility="Public"><AttributeList><BooleanAttribute Name="ExternalAccessible" SystemDefined="true">false</BooleanAttribute><BooleanAttribute Name="ExternalVisible" SystemDefined="true">false</BooleanAttribute><BooleanAttribute Name="ExternalWritable" SystemDefined="true">false</BooleanAttribute><BooleanAttribute Name="SetPoint" SystemDefined="true">true</BooleanAttribute></AttributeList><Sections><Section Name="None"><Member Name="Mod_TCP_Connect" Datatype="&quot;Mod_Connect_Data&quot;"><Sections><Section Name="None"><Member Name="connectParamClient" Datatype="TCON_IP_v4" Version="1.0"><Sections><Section Name="None"><Member Name="InterfaceId" Datatype="HW_ANY"><Subelement Path="1"><StartValue>64</StartValue></Subelement><Subelement Path="2"><StartValue>64</StartValue></Subelement><Subelement Path="3"><StartValue>64</StartValue></Subelement><Subelement Path="4"><StartValue>64</StartValue></Subelement><Subelement Path="5"><StartValue>64</StartValue></Subelement><Subelement Path="6"><StartValue>64</StartValue></Subelement></Member><Member Name="ID" Datatype="CONN_OUC"><Subelement Path="1"><StartValue>1</StartValue></Subelement><Subelement Path="2"><StartValue>2</StartValue></Subelement><Subelement Path="3"><StartValue>3</StartValue></Subelement><Subelement Path="4"><StartValue>4</StartValue></Subelement><Subelement Path="5"><StartValue>5</StartValue></Subelement><Subelement Path="6"><StartValue>6</StartValue></Subelement></Member><Member Name="ConnectionType" Datatype="Byte"><Subelement Path="1"><StartValue>16#0B</StartValue></Subelement><Subelement Path="2"><StartValue>16#0B</StartValue></Subelement><Subelement Path="3"><StartValue>16#0B</StartValue></Subelement><Subelement Path="4"><StartValue>16#0B</StartValue></Subelement><Subelement Path="5"><StartValue>16#0B</StartValue></Subelement><Subelement Path="6"><StartValue>16#0B</StartValue></Subelement></Member><Member Name="ActiveEstablished" Datatype="Bool"><Subelement Path="1"><StartValue>true</StartValue></Subelement><Subelement Path="2"><StartValue>true</StartValue></Subelement><Subelement Path="3"><StartValue>true</StartValue></Subelement><Subelement Path="4"><StartValue>true</StartValue></Subelement><Subelement Path="5"><StartValue>true</StartValue></Subelement><Subelement Path="6"><StartValue>true</StartValue></Subelement></Member><Member Name="RemoteAddress" Datatype="IP_V4" Version="1.0"><Sections><Section Name="None"><Member Name="ADDR" Datatype="Array[1..4] of Byte"><Subelement Path="1,1"><StartValue>192</StartValue></Subelement><Subelement Path="1,2"><StartValue>168</StartValue></Subelement><Subelement Path="1,3"><StartValue>0</StartValue></Subelement><Subelement Path="1,4"><StartValue>21</StartValue></Subelement><Subelement Path="2,1"><StartValue>192</StartValue></Subelement><Subelement Path="2,2"><StartValue>168</StartValue></Subelement><Subelement Path="2,3"><StartValue>0</StartValue></Subelement><Subelement Path="2,4"><StartValue>22</StartValue></Subelement><Subelement Path="3,1"><StartValue>192</StartValue></Subelement><Subelement Path="3,2"><StartValue>168</StartValue></Subelement><Subelement Path="3,3"><StartValue>0</StartValue></Subelement><Subelement Path="3,4"><StartValue>23</StartValue></Subelement><Subelement Path="4,1"><StartValue>192</StartValue></Subelement><Subelement Path="4,2"><StartValue>168</StartValue></Subelement><Subelement Path="4,3"><StartValue>0</StartValue></Subelement><Subelement Path="4,4"><StartValue>24</StartValue></Subelement><Subelement Path="5,1"><StartValue>192</StartValue></Subelement><Subelement Path="5,2"><StartValue>168</StartValue></Subelement><Subelement Path="5,3"><StartValue>0</StartValue></Subelement><Subelement Path="5,4"><StartValue>25</StartValue></Subelement><Subelement Path="6,1"><StartValue>192</StartValue></Subelement><Subelement Path="6,2"><StartValue>168</StartValue></Subelement><Subelement Path="6,3"><StartValue>0</StartValue></Subelement><Subelement Path="6,4"><StartValue>26</StartValue></Subelement></Member></Section></Sections></Member><Member Name="RemotePort" Datatype="UInt"><Subelement Path="1"><StartValue>502</StartValue></Subelement><Subelement Path="2"><StartValue>502</StartValue></Subelement><Subelement Path="3"><StartValue>502</StartValue></Subelement><Subelement Path="4"><StartValue>502</StartValue></Subelement><Subelement Path="5"><StartValue>502</StartValue></Subelement><Subelement Path="6"><StartValue>502</StartValue></Subelement></Member><Member Name="LocalPort" Datatype="UInt"><Subelement Path="2"><StartValue>0</StartValue></Subelement><Subelement Path="3"><StartValue>0</StartValue></Subelement><Subelement Path="4"><StartValue>0</StartValue></Subelement><Subelement Path="5"><StartValue>0</StartValue></Subelement><Subelement Path="6"><StartValue>0</StartValue></Subelement></Member></Section></Sections></Member></Section></Sections></Member><Member Name="Mod_Client" Datatype="Array[1..6] of &quot;Mod_Client_Data&quot;"><Sections><Section Name="None"><Member Name="request" Datatype="Bool"><Subelement Path="1,1"><StartValue>false</StartValue></Subelement><Subelement Path="1,2"><StartValue>false</StartValue></Subelement><Subelement Path="1,3"><StartValue>false</StartValue></Subelement><Subelement Path="1,4"><StartValue>false</StartValue></Subelement><Subelement Path="1,5"><StartValue>false</StartValue></Subelement><Subelement Path="1,6"><StartValue>false</StartValue></Subelement><Subelement Path="2,1"><StartValue>false</StartValue></Subelement><Subelement Path="2,2"><StartValue>false</StartValue></Subelement><Subelement Path="2,3"><StartValue>false</StartValue></Subelement><Subelement Path="2,4"><StartValue>false</StartValue></Subelement><Subelement Path="2,5"><StartValue>false</StartValue></Subelement><Subelement Path="2,6"><StartValue>false</StartValue></Subelement><Subelement Path="3,1"><StartValue>false</StartValue></Subelement><Subelement Path="3,2"><StartValue>false</StartValue></Subelement><Subelement Path="3,3"><StartValue>false</StartValue></Subelement><Subelement Path="3,4"><StartValue>false</StartValue></Subelement><Subelement Path="3,5"><StartValue>false</StartValue></Subelement><Subelement Path="3,6"><StartValue>false</StartValue></Subelement><Subelement Path="4,1"><StartValue>false</StartValue></Subelement><Subelement Path="4,2"><StartValue>false</StartValue></Subelement><Subelement Path="4,3"><StartValue>false</StartValue></Subelement><Subelement Path="4,4"><StartValue>false</StartValue></Subelement><Subelement Path="4,5"><StartValue>false</StartValue></Subelement><Subelement Path="4,6"><StartValue>false</StartValue></Subelement><Subelement Path="5,1"><StartValue>false</StartValue></Subelement><Subelement Path="5,2"><StartValue>false</StartValue></Subelement><Subelement Path="5,3"><StartValue>false</StartValue></Subelement><Subelement Path="5,4"><StartValue>false</StartValue></Subelement><Subelement Path="5,5"><StartValue>false</StartValue></Subelement><Subelement Path="5,6"><StartValue>false</StartValue></Subelement><Subelement Path="6,1"><StartValue>false</StartValue></Subelement><Subelement Path="6,2"><StartValue>false</StartValue></Subelement><Subelement Path="6,3"><StartValue>false</StartValue></Subelement><Subelement Path="6,4"><StartValue>false</StartValue></Subelement><Subelement Path="6,5"><StartValue>false</StartValue></Subelement><Subelement Path="6,6"><StartValue>false</StartValue></Subelement></Member><Member Name="enable" Datatype="Bool"><Subelement Path="1,1"><StartValue>false</StartValue></Subelement><Subelement Path="1,2"><StartValue>false</StartValue></Subelement><Subelement Path="1,3"><StartValue>false</StartValue></Subelement><Subelement Path="1,4"><StartValue>false</StartValue></Subelement><Subelement Path="1,5"><StartValue>false</StartValue></Subelement><Subelement Path="1,6"><StartValue>false</StartValue></Subelement><Subelement Path="2,1"><StartValue>false</StartValue></Subelement><Subelement Path="2,2"><StartValue>false</StartValue></Subelement><Subelement Path="2,3"><StartValue>false</StartValue></Subelement><Subelement Path="2,4"><StartValue>false</StartValue></Subelement><Subelement Path="2,5"><StartValue>false</StartValue></Subelement><Subelement Path="2,6"><StartValue>false</StartValue></Subelement><Subelement Path="3,1"><StartValue>false</StartValue></Subelement><Subelement Path="3,2"><StartValue>false</StartValue></Subelement><Subelement Path="3,3"><StartValue>false</StartValue></Subelement><Subelement Path="3,4"><StartValue>false</StartValue></Subelement><Subelement Path="3,5"><StartValue>false</StartValue></Subelement><Subelement Path="3,6"><StartValue>false</StartValue></Subelement><Subelement Path="4,1"><StartValue>false</StartValue></Subelement><Subelement Path="4,2"><StartValue>false</StartValue></Subelement><Subelement Path="4,3"><StartValue>false</StartValue></Subelement><Subelement Path="4,4"><StartValue>false</StartValue></Subelement><Subelement Path="4,5"><StartValue>false</StartValue></Subelement><Subelement Path="4,6"><StartValue>false</StartValue></Subelement><Subelement Path="5,1"><StartValue>false</StartValue></Subelement><Subelement Path="5,2"><StartValue>false</StartValue></Subelement><Subelement Path="5,3"><StartValue>false</StartValue></Subelement><Subelement Path="5,4"><StartValue>false</StartValue></Subelement><Subelement Path="5,5"><StartValue>false</StartValue></Subelement><Subelement Path="5,6"><StartValue>false</StartValue></Subelement><Subelement Path="6,1"><StartValue>false</StartValue></Subelement><Subelement Path="6,2"><StartValue>false</StartValue></Subelement><Subelement Path="6,3"><StartValue>false</StartValue></Subelement><Subelement Path="6,4"><StartValue>false</StartValue></Subelement><Subelement Path="6,5"><StartValue>false</StartValue></Subelement><Subelement Path="6,6"><StartValue>false</StartValue></Subelement></Member><Member Name="disconnect" Datatype="Bool"><Subelement Path="1,1"><StartValue>false</StartValue></Subelement><Subelement Path="1,2"><StartValue>false</StartValue></Subelement><Subelement Path="1,3"><StartValue>false</StartValue></Subelement><Subelement Path="1,4"><StartValue>false</StartValue></Subelement><Subelement Path="1,5"><StartValue>false</StartValue></Subelement><Subelement Path="1,6"><StartValue>false</StartValue></Subelement><Subelement Path="2,1"><StartValue>false</StartValue></Subelement><Subelement Path="2,2"><StartValue>false</StartValue></Subelement><Subelement Path="2,3"><StartValue>false</StartValue></Subelement><Subelement Path="2,4"><StartValue>false</StartValue></Subelement><Subelement Path="2,5"><StartValue>false</StartValue></Subelement><Subelement Path="2,6"><StartValue>false</StartValue></Subelement><Subelement Path="3,1"><StartValue>false</StartValue></Subelement><Subelement Path="3,2"><StartValue>false</StartValue></Subelement><Subelement Path="3,3"><StartValue>false</StartValue></Subelement><Subelement Path="3,4"><StartValue>false</StartValue></Subelement><Subelement Path="3,5"><StartValue>false</StartValue></Subelement><Subelement Path="3,6"><StartValue>false</StartValue></Subelement><Subelement Path="4,1"><StartValue>false</StartValue></Subelement><Subelement Path="4,2"><StartValue>false</StartValue></Subelement><Subelement Path="4,3"><StartValue>false</StartValue></Subelement><Subelement Path="4,4"><StartValue>false</StartValue></Subelement><Subelement Path="4,5"><StartValue>false</StartValue></Subelement><Subelement Path="4,6"><StartValue>false</StartValue></Subelement><Subelement Path="5,1"><StartValue>false</StartValue></Subelement><Subelement Path="5,2"><StartValue>false</StartValue></Subelement><Subelement Path="5,3"><StartValue>false</StartValue></Subelement><Subelement Path="5,4"><StartValue>false</StartValue></Subelement><Subelement Path="5,5"><StartValue>false</StartValue></Subelement><Subelement Path="5,6"><StartValue>false</StartValue></Subelement><Subelement Path="6,1"><StartValue>false</StartValue></Subelement><Subelement Path="6,2"><StartValue>false</StartValue></Subelement><Subelement Path="6,3"><StartValue>false</StartValue></Subelement><Subelement Path="6,4"><StartValue>false</StartValue></Subelement><Subelement Path="6,5"><StartValue>false</StartValue></Subelement><Subelement Path="6,6"><StartValue>false</StartValue></Subelement></Member><Member Name="done" Datatype="Bool"><Subelement Path="1,1"><StartValue>false</StartValue></Subelement><Subelement Path="1,2"><StartValue>false</StartValue></Subelement><Subelement Path="1,3"><StartValue>false</StartValue></Subelement><Subelement Path="1,4"><StartValue>false</StartValue></Subelement><Subelement Path="1,5"><StartValue>false</StartValue></Subelement><Subelement Path="1,6"><StartValue>false</StartValue></Subelement><Subelement Path="2,1"><StartValue>false</StartValue></Subelement><Subelement Path="2,2"><StartValue>false</StartValue></Subelement><Subelement Path="2,3"><StartValue>false</StartValue></Subelement><Subelement Path="2,4"><StartValue>false</StartValue></Subelement><Subelement Path="2,5"><StartValue>false</StartValue></Subelement><Subelement Path="2,6"><StartValue>false</StartValue></Subelement><Subelement Path="3,1"><StartValue>false</StartValue></Subelement><Subelement Path="3,2"><StartValue>false</StartValue></Subelement><Subelement Path="3,3"><StartValue>false</StartValue></Subelement><Subelement Path="3,4"><StartValue>false</StartValue></Subelement><Subelement Path="3,5"><StartValue>false</StartValue></Subelement><Subelement Path="3,6"><StartValue>false</StartValue></Subelement><Subelement Path="4,1"><StartValue>false</StartValue></Subelement><Subelement Path="4,2"><StartValue>false</StartValue></Subelement><Subelement Path="4,3"><StartValue>false</StartValue></Subelement><Subelement Path="4,4"><StartValue>false</StartValue></Subelement><Subelement Path="4,5"><StartValue>false</StartValue></Subelement><Subelement Path="4,6"><StartValue>false</StartValue></Subelement><Subelement Path="5,1"><StartValue>false</StartValue></Subelement><Subelement Path="5,2"><StartValue>false</StartValue></Subelement><Subelement Path="5,3"><StartValue>false</StartValue></Subelement><Subelement Path="5,4"><StartValue>false</StartValue></Subelement><Subelement Path="5,5"><StartValue>false</StartValue></Subelement><Subelement Path="5,6"><StartValue>false</StartValue></Subelement><Subelement Path="6,1"><StartValue>false</StartValue></Subelement><Subelement Path="6,2"><StartValue>false</StartValue></Subelement><Subelement Path="6,3"><StartValue>false</StartValue></Subelement><Subelement Path="6,4"><StartValue>false</StartValue></Subelement><Subelement Path="6,5"><StartValue>false</StartValue></Subelement><Subelement Path="6,6"><StartValue>false</StartValue></Subelement></Member><Member Name="busy" Datatype="Bool"><Subelement Path="1,1"><StartValue>false</StartValue></Subelement><Subelement Path="1,2"><StartValue>false</StartValue></Subelement><Subelement Path="1,3"><StartValue>false</StartValue></Subelement><Subelement Path="1,4"><StartValue>false</StartValue></Subelement><Subelement Path="1,5"><StartValue>false</StartValue></Subelement><Subelement Path="1,6"><StartValue>false</StartValue></Subelement><Subelement Path="2,1"><StartValue>false</StartValue></Subelement><Subelement Path="2,2"><StartValue>false</StartValue></Subelement><Subelement Path="2,3"><StartValue>false</StartValue></Subelement><Subelement Path="2,4"><StartValue>false</StartValue></Subelement><Subelement Path="2,5"><StartValue>false</StartValue></Subelement><Subelement Path="2,6"><StartValue>false</StartValue></Subelement><Subelement Path="3,1"><StartValue>false</StartValue></Subelement><Subelement Path="3,2"><StartValue>false</StartValue></Subelement><Subelement Path="3,3"><StartValue>false</StartValue></Subelement><Subelement Path="3,4"><StartValue>false</StartValue></Subelement><Subelement Path="3,5"><StartValue>false</StartValue></Subelement><Subelement Path="3,6"><StartValue>false</StartValue></Subelement><Subelement Path="4,1"><StartValue>false</StartValue></Subelement><Subelement Path="4,2"><StartValue>false</StartValue></Subelement><Subelement Path="4,3"><StartValue>false</StartValue></Subelement><Subelement Path="4,4"><StartValue>false</StartValue></Subelement><Subelement Path="4,5"><StartValue>false</StartValue></Subelement><Subelement Path="4,6"><StartValue>false</StartValue></Subelement><Subelement Path="5,1"><StartValue>false</StartValue></Subelement><Subelement Path="5,2"><StartValue>false</StartValue></Subelement><Subelement Path="5,3"><StartValue>false</StartValue></Subelement><Subelement Path="5,4"><StartValue>false</StartValue></Subelement><Subelement Path="5,5"><StartValue>false</StartValue></Subelement><Subelement Path="5,6"><StartValue>false</StartValue></Subelement><Subelement Path="6,1"><StartValue>false</StartValue></Subelement><Subelement Path="6,2"><StartValue>false</StartValue></Subelement><Subelement Path="6,3"><StartValue>false</StartValue></Subelement><Subelement Path="6,4"><StartValue>false</StartValue></Subelement><Subelement Path="6,5"><StartValue>false</StartValue></Subelement><Subelement Path="6,6"><StartValue>false</StartValue></Subelement></Member><Member Name="error" Datatype="Bool"><Subelement Path="1,1"><StartValue>false</StartValue></Subelement><Subelement Path="1,2"><StartValue>false</StartValue></Subelement><Subelement Path="1,3"><StartValue>false</StartValue></Subelement><Subelement Path="1,4"><StartValue>false</StartValue></Subelement><Subelement Path="1,5"><StartValue>false</StartValue></Subelement><Subelement Path="1,6"><StartValue>false</StartValue></Subelement><Subelement Path="2,1"><StartValue>false</StartValue></Subelement><Subelement Path="2,2"><StartValue>false</StartValue></Subelement><Subelement Path="2,3"><StartValue>false</StartValue></Subelement><Subelement Path="2,4"><StartValue>false</StartValue></Subelement><Subelement Path="2,5"><StartValue>false</StartValue></Subelement><Subelement Path="2,6"><StartValue>false</StartValue></Subelement><Subelement Path="3,1"><StartValue>false</StartValue></Subelement><Subelement Path="3,2"><StartValue>false</StartValue></Subelement><Subelement Path="3,3"><StartValue>false</StartValue></Subelement><Subelement Path="3,4"><StartValue>false</StartValue></Subelement><Subelement Path="3,5"><StartValue>false</StartValue></Subelement><Subelement Path="3,6"><StartValue>false</StartValue></Subelement><Subelement Path="4,1"><StartValue>false</StartValue></Subelement><Subelement Path="4,2"><StartValue>false</StartValue></Subelement><Subelement Path="4,3"><StartValue>false</StartValue></Subelement><Subelement Path="4,4"><StartValue>false</StartValue></Subelement><Subelement Path="4,5"><StartValue>false</StartValue></Subelement><Subelement Path="4,6"><StartValue>false</StartValue></Subelement><Subelement Path="5,1"><StartValue>false</StartValue></Subelement><Subelement Path="5,2"><StartValue>false</StartValue></Subelement><Subelement Path="5,3"><StartValue>false</StartValue></Subelement><Subelement Path="5,4"><StartValue>false</StartValue></Subelement><Subelement Path="5,5"><StartValue>false</StartValue></Subelement><Subelement Path="5,6"><StartValue>false</StartValue></Subelement><Subelement Path="6,1"><StartValue>false</StartValue></Subelement><Subelement Path="6,2"><StartValue>false</StartValue></Subelement><Subelement Path="6,3"><StartValue>false</StartValue></Subelement><Subelement Path="6,4"><StartValue>false</StartValue></Subelement><Subelement Path="6,5"><StartValue>false</StartValue></Subelement><Subelement Path="6,6"><StartValue>false</StartValue></Subelement></Member><Member Name="status" Datatype="Word"><Subelement Path="1,1"><StartValue>16#0</StartValue></Subelement><Subelement Path="1,2"><StartValue>16#0</StartValue></Subelement><Subelement Path="1,3"><StartValue>16#0</StartValue></Subelement><Subelement Path="1,4"><StartValue>16#0</StartValue></Subelement><Subelement Path="1,5"><StartValue>16#0</StartValue></Subelement><Subelement Path="1,6"><StartValue>16#0</StartValue></Subelement><Subelement Path="2,1"><StartValue>16#0</StartValue></Subelement><Subelement Path="2,2"><StartValue>16#0</StartValue></Subelement><Subelement Path="2,3"><StartValue>16#0</StartValue></Subelement><Subelement Path="2,4"><StartValue>16#0</StartValue></Subelement><Subelement Path="2,5"><StartValue>16#0</StartValue></Subelement><Subelement Path="2,6"><StartValue>16#0</StartValue></Subelement><Subelement Path="3,1"><StartValue>16#0</StartValue></Subelement><Subelement Path="3,2"><StartValue>16#0</StartValue></Subelement><Subelement Path="3,3"><StartValue>16#0</StartValue></Subelement><Subelement Path="3,4"><StartValue>16#0</StartValue></Subelement><Subelement Path="3,5"><StartValue>16#0</StartValue></Subelement><Subelement Path="3,6"><StartValue>16#0</StartValue></Subelement><Subelement Path="4,1"><StartValue>16#0</StartValue></Subelement><Subelement Path="4,2"><StartValue>16#0</StartValue></Subelement><Subelement Path="4,3"><StartValue>16#0</StartValue></Subelement><Subelement Path="4,4"><StartValue>16#0</StartValue></Subelement><Subelement Path="4,5"><StartValue>16#0</StartValue></Subelement><Subelement Path="4,6"><StartValue>16#0</StartValue></Subelement><Subelement Path="5,1"><StartValue>16#0</StartValue></Subelement><Subelement Path="5,2"><StartValue>16#0</StartValue></Subelement><Subelement Path="5,3"><StartValue>16#0</StartValue></Subelement><Subelement Path="5,4"><StartValue>16#0</StartValue></Subelement><Subelement Path="5,5"><StartValue>16#0</StartValue></Subelement><Subelement Path="5,6"><StartValue>16#0</StartValue></Subelement><Subelement Path="6,1"><StartValue>16#0</StartValue></Subelement><Subelement Path="6,2"><StartValue>16#0</StartValue></Subelement><Subelement Path="6,3"><StartValue>16#0</StartValue></Subelement><Subelement Path="6,4"><StartValue>16#0</StartValue></Subelement><Subelement Path="6,5"><StartValue>16#0</StartValue></Subelement><Subelement Path="6,6"><StartValue>16#0</StartValue></Subelement></Member><Member Name="statusSave" Datatype="Word"><Subelement Path="1,1"><StartValue>16#0</StartValue></Subelement><Subelement Path="1,2"><StartValue>16#0</StartValue></Subelement><Subelement Path="1,3"><StartValue>16#0</StartValue></Subelement><Subelement Path="1,4"><StartValue>16#0</StartValue></Subelement><Subelement Path="1,5"><StartValue>16#0</StartValue></Subelement><Subelement Path="1,6"><StartValue>16#0</StartValue></Subelement><Subelement Path="2,1"><StartValue>16#0</StartValue></Subelement><Subelement Path="2,2"><StartValue>16#0</StartValue></Subelement><Subelement Path="2,3"><StartValue>16#0</StartValue></Subelement><Subelement Path="2,4"><StartValue>16#0</StartValue></Subelement><Subelement Path="2,5"><StartValue>16#0</StartValue></Subelement><Subelement Path="2,6"><StartValue>16#0</StartValue></Subelement><Subelement Path="3,1"><StartValue>16#0</StartValue></Subelement><Subelement Path="3,2"><StartValue>16#0</StartValue></Subelement><Subelement Path="3,3"><StartValue>16#0</StartValue></Subelement><Subelement Path="3,4"><StartValue>16#0</StartValue></Subelement><Subelement Path="3,5"><StartValue>16#0</StartValue></Subelement><Subelement Path="3,6"><StartValue>16#0</StartValue></Subelement><Subelement Path="4,1"><StartValue>16#0</StartValue></Subelement><Subelement Path="4,2"><StartValue>16#0</StartValue></Subelement><Subelement Path="4,3"><StartValue>16#0</StartValue></Subelement><Subelement Path="4,4"><StartValue>16#0</StartValue></Subelement><Subelement Path="4,5"><StartValue>16#0</StartValue></Subelement><Subelement Path="4,6"><StartValue>16#0</StartValue></Subelement><Subelement Path="5,1"><StartValue>16#0</StartValue></Subelement><Subelement Path="5,2"><StartValue>16#0</StartValue></Subelement><Subelement Path="5,3"><StartValue>16#0</StartValue></Subelement><Subelement Path="5,4"><StartValue>16#0</StartValue></Subelement><Subelement Path="5,5"><StartValue>16#0</StartValue></Subelement><Subelement Path="5,6"><StartValue>16#0</StartValue></Subelement><Subelement Path="6,1"><StartValue>16#0</StartValue></Subelement><Subelement Path="6,2"><StartValue>16#0</StartValue></Subelement><Subelement Path="6,3"><StartValue>16#0</StartValue></Subelement><Subelement Path="6,4"><StartValue>16#0</StartValue></Subelement><Subelement Path="6,5"><StartValue>16#0</StartValue></Subelement><Subelement Path="6,6"><StartValue>16#0</StartValue></Subelement></Member><Member Name="modbusMode" Datatype="USInt"><Subelement Path="1,1"><StartValue>1</StartValue></Subelement><Subelement Path="1,2"><StartValue>0</StartValue></Subelement><Subelement Path="1,3"><StartValue>1</StartValue></Subelement><Subelement Path="1,4"><StartValue>0</StartValue></Subelement><Subelement Path="1,5"><StartValue>0</StartValue></Subelement><Subelement Path="1,6"><StartValue>1</StartValue></Subelement><Subelement Path="2,1"><StartValue>1</StartValue></Subelement><Subelement Path="2,2"><StartValue>0</StartValue></Subelement><Subelement Path="2,3"><StartValue>1</StartValue></Subelement><Subelement Path="2,4"><StartValue>0</StartValue></Subelement><Subelement Path="2,5"><StartValue>0</StartValue></Subelement><Subelement Path="2,6"><StartValue>1</StartValue></Subelement><Subelement Path="3,1"><StartValue>1</StartValue></Subelement><Subelement Path="3,2"><StartValue>0</StartValue></Subelement><Subelement Path="3,3"><StartValue>1</StartValue></Subelement><Subelement Path="3,4"><StartValue>0</StartValue></Subelement><Subelement Path="3,5"><StartValue>0</StartValue></Subelement><Subelement Path="3,6"><StartValue>1</StartValue></Subelement><Subelement Path="4,1"><StartValue>1</StartValue></Subelement><Subelement Path="4,2"><StartValue>0</StartValue></Subelement><Subelement Path="4,3"><StartValue>1</StartValue></Subelement><Subelement Path="4,4"><StartValue>0</StartValue></Subelement><Subelement Path="4,5"><StartValue>0</StartValue></Subelement><Subelement Path="4,6"><StartValue>1</StartValue></Subelement><Subelement Path="5,1"><StartValue>1</StartValue></Subelement><Subelement Path="5,2"><StartValue>0</StartValue></Subelement><Subelement Path="5,3"><StartValue>1</StartValue></Subelement><Subelement Path="5,4"><StartValue>0</StartValue></Subelement><Subelement Path="5,5"><StartValue>0</StartValue></Subelement><Subelement Path="5,6"><StartValue>1</StartValue></Subelement><Subelement Path="6,1"><StartValue>1</StartValue></Subelement><Subelement Path="6,2"><StartValue>0</StartValue></Subelement><Subelement Path="6,3"><StartValue>1</StartValue></Subelement><Subelement Path="6,4"><StartValue>0</StartValue></Subelement><Subelement Path="6,5"><StartValue>0</StartValue></Subelement><Subelement Path="6,6"><StartValue>1</StartValue></Subelement></Member><Member Name="modbusDataAddress" Datatype="UDInt"><Subelement Path="1,1"><StartValue>40908</StartValue></Subelement><Subelement Path="1,2"><StartValue>40001</StartValue></Subelement><Subelement Path="1,3"><StartValue>40302</StartValue></Subelement><Subelement Path="1,4"><StartValue>0</StartValue></Subelement><Subelement Path="1,5"><StartValue>1</StartValue></Subelement><Subelement Path="1,6"><StartValue>0</StartValue></Subelement><Subelement Path="2,1"><StartValue>40908</StartValue></Subelement><Subelement Path="2,2"><StartValue>40001</StartValue></Subelement><Subelement Path="2,3"><StartValue>40302</StartValue></Subelement><Subelement Path="2,4"><StartValue>0</StartValue></Subelement><Subelement Path="2,5"><StartValue>1</StartValue></Subelement><Subelement Path="2,6"><StartValue>0</StartValue></Subelement><Subelement Path="3,1"><StartValue>40908</StartValue></Subelement><Subelement Path="3,2"><StartValue>40001</StartValue></Subelement><Subelement Path="3,3"><StartValue>40302</StartValue></Subelement><Subelement Path="3,4"><StartValue>0</StartValue></Subelement><Subelement Path="3,5"><StartValue>1</StartValue></Subelement><Subelement Path="3,6"><StartValue>0</StartValue></Subelement><Subelement Path="4,1"><StartValue>40908</StartValue></Subelement><Subelement Path="4,2"><StartValue>40001</StartValue></Subelement><Subelement Path="4,3"><StartValue>40302</StartValue></Subelement><Subelement Path="4,4"><StartValue>0</StartValue></Subelement><Subelement Path="4,5"><StartValue>1</StartValue></Subelement><Subelement Path="4,6"><StartValue>0</StartValue></Subelement><Subelement Path="5,1"><StartValue>40908</StartValue></Subelement><Subelement Path="5,2"><StartValue>40001</StartValue></Subelement><Subelement Path="5,3"><StartValue>40302</StartValue></Subelement><Subelement Path="5,4"><StartValue>0</StartValue></Subelement><Subelement Path="5,5"><StartValue>1</StartValue></Subelement><Subelement Path="5,6"><StartValue>0</StartValue></Subelement><Subelement Path="6,1"><StartValue>40908</StartValue></Subelement><Subelement Path="6,2"><StartValue>40001</StartValue></Subelement><Subelement Path="6,3"><StartValue>40302</StartValue></Subelement><Subelement Path="6,4"><StartValue>0</StartValue></Subelement><Subelement Path="6,5"><StartValue>1</StartValue></Subelement><Subelement Path="6,6"><StartValue>0</StartValue></Subelement></Member><Member Name="modbusDataLen" Datatype="UInt"><Subelement Path="1,1"><StartValue>1</StartValue></Subelement><Subelement Path="1,2"><StartValue>6</StartValue></Subelement><Subelement Path="1,3"><StartValue>1</StartValue></Subelement><Subelement Path="1,4"><StartValue>0</StartValue></Subelement><Subelement Path="1,5"><StartValue>32</StartValue></Subelement><Subelement Path="1,6"><StartValue>1</StartValue></Subelement><Subelement Path="2,1"><StartValue>1</StartValue></Subelement><Subelement Path="2,2"><StartValue>6</StartValue></Subelement><Subelement Path="2,3"><StartValue>1</StartValue></Subelement><Subelement Path="2,4"><StartValue>0</StartValue></Subelement><Subelement Path="2,5"><StartValue>32</StartValue></Subelement><Subelement Path="2,6"><StartValue>1</StartValue></Subelement><Subelement Path="3,1"><StartValue>1</StartValue></Subelement><Subelement Path="3,2"><StartValue>6</StartValue></Subelement><Subelement Path="3,3"><StartValue>1</StartValue></Subelement><Subelement Path="3,4"><StartValue>0</StartValue></Subelement><Subelement Path="3,5"><StartValue>32</StartValue></Subelement><Subelement Path="3,6"><StartValue>1</StartValue></Subelement><Subelement Path="4,1"><StartValue>1</StartValue></Subelement><Subelement Path="4,2"><StartValue>6</StartValue></Subelement><Subelement Path="4,3"><StartValue>1</StartValue></Subelement><Subelement Path="4,4"><StartValue>0</StartValue></Subelement><Subelement Path="4,5"><StartValue>32</StartValue></Subelement><Subelement Path="4,6"><StartValue>1</StartValue></Subelement><Subelement Path="5,1"><StartValue>1</StartValue></Subelement><Subelement Path="5,2"><StartValue>6</StartValue></Subelement><Subelement Path="5,3"><StartValue>1</StartValue></Subelement><Subelement Path="5,4"><StartValue>0</StartValue></Subelement><Subelement Path="5,5"><StartValue>32</StartValue></Subelement><Subelement Path="5,6"><StartValue>1</StartValue></Subelement><Subelement Path="6,1"><StartValue>1</StartValue></Subelement><Subelement Path="6,2"><StartValue>6</StartValue></Subelement><Subelement Path="6,3"><StartValue>1</StartValue></Subelement><Subelement Path="6,4"><StartValue>0</StartValue></Subelement><Subelement Path="6,5"><StartValue>32</StartValue></Subelement><Subelement Path="6,6"><StartValue>1</StartValue></Subelement></Member></Section></Sections></Member></Section></Sections></Member>
    <Member Name="TCP_Data_Station5" Datatype="Array[1..6] of &quot;Mod_TCP_Data&quot;" Remanence="Retain" Accessibility="Public"><AttributeList><BooleanAttribute Name="ExternalAccessible" SystemDefined="true">false</BooleanAttribute><BooleanAttribute Name="ExternalVisible" SystemDefined="true">false</BooleanAttribute><BooleanAttribute Name="ExternalWritable" SystemDefined="true">false</BooleanAttribute><BooleanAttribute Name="SetPoint" SystemDefined="true">false</BooleanAttribute></AttributeList><Sections><Section Name="None"><Member Name="Mod_TCP_Connect" Datatype="&quot;Mod_Connect_Data&quot;"><Sections><Section Name="None"><Member Name="connectParamClient" Datatype="TCON_IP_v4" Version="1.0"><Sections><Section Name="None"><Member Name="InterfaceId" Datatype="HW_ANY"><Subelement Path="1"><StartValue>64</StartValue></Subelement><Subelement Path="2"><StartValue>64</StartValue></Subelement><Subelement Path="3"><StartValue>64</StartValue></Subelement><Subelement Path="4"><StartValue>64</StartValue></Subelement><Subelement Path="5"><StartValue>64</StartValue></Subelement><Subelement Path="6"><StartValue>64</StartValue></Subelement></Member><Member Name="ID" Datatype="CONN_OUC"><Subelement Path="1"><StartValue>11</StartValue></Subelement><Subelement Path="2"><StartValue>12</StartValue></Subelement><Subelement Path="3"><StartValue>13</StartValue></Subelement><Subelement Path="4"><StartValue>14</StartValue></Subelement><Subelement Path="5"><StartValue>15</StartValue></Subelement><Subelement Path="6"><StartValue>16</StartValue></Subelement></Member><Member Name="ConnectionType" Datatype="Byte"><Subelement Path="1"><StartValue>16#0B</StartValue></Subelement><Subelement Path="2"><StartValue>16#0B</StartValue></Subelement><Subelement Path="3"><StartValue>16#0B</StartValue></Subelement><Subelement Path="4"><StartValue>16#0B</StartValue></Subelement><Subelement Path="5"><StartValue>16#0B</StartValue></Subelement><Subelement Path="6"><StartValue>16#0B</StartValue></Subelement></Member><Member Name="ActiveEstablished" Datatype="Bool"><Subelement Path="1"><StartValue>true</StartValue></Subelement><Subelement Path="2"><StartValue>True</StartValue></Subelement><Subelement Path="3"><StartValue>True</StartValue></Subelement><Subelement Path="4"><StartValue>True</StartValue></Subelement><Subelement Path="5"><StartValue>True</StartValue></Subelement><Subelement Path="6"><StartValue>True</StartValue></Subelement></Member><Member Name="RemoteAddress" Datatype="IP_V4" Version="1.0"><Sections><Section Name="None"><Member Name="ADDR" Datatype="Array[1..4] of Byte"><Subelement Path="1,1"><StartValue>192</StartValue></Subelement><Subelement Path="1,2"><StartValue>168</StartValue></Subelement><Subelement Path="1,3"><StartValue>0</StartValue></Subelement><Subelement Path="1,4"><StartValue>31</StartValue></Subelement><Subelement Path="2,1"><StartValue>192</StartValue></Subelement><Subelement Path="2,2"><StartValue>168</StartValue></Subelement><Subelement Path="2,3"><StartValue>0</StartValue></Subelement><Subelement Path="2,4"><StartValue>32</StartValue></Subelement><Subelement Path="3,1"><StartValue>192</StartValue></Subelement><Subelement Path="3,2"><StartValue>168</StartValue></Subelement><Subelement Path="3,3"><StartValue>0</StartValue></Subelement><Subelement Path="3,4"><StartValue>33</StartValue></Subelement><Subelement Path="4,1"><StartValue>192</StartValue></Subelement><Subelement Path="4,2"><StartValue>168</StartValue></Subelement><Subelement Path="4,3"><StartValue>0</StartValue></Subelement><Subelement Path="4,4"><StartValue>34</StartValue></Subelement><Subelement Path="5,1"><StartValue>192</StartValue></Subelement><Subelement Path="5,2"><StartValue>168</StartValue></Subelement><Subelement Path="5,3"><StartValue>0</StartValue></Subelement><Subelement Path="5,4"><StartValue>35</StartValue></Subelement><Subelement Path="6,1"><StartValue>192</StartValue></Subelement><Subelement Path="6,2"><StartValue>168</StartValue></Subelement><Subelement Path="6,3"><StartValue>0</StartValue></Subelement><Subelement Path="6,4"><StartValue>36</StartValue></Subelement></Member></Section></Sections></Member><Member Name="RemotePort" Datatype="UInt"><Subelement Path="1"><StartValue>502</StartValue></Subelement><Subelement Path="2"><StartValue>502</StartValue></Subelement><Subelement Path="3"><StartValue>502</StartValue></Subelement><Subelement Path="4"><StartValue>502</StartValue></Subelement><Subelement Path="5"><StartValue>502</StartValue></Subelement><Subelement Path="6"><StartValue>502</StartValue></Subelement></Member><Member Name="LocalPort" Datatype="UInt"><Subelement Path="1"><StartValue>0</StartValue></Subelement><Subelement Path="2"><StartValue>0</StartValue></Subelement><Subelement Path="3"><StartValue>0</StartValue></Subelement><Subelement Path="4"><StartValue>0</StartValue></Subelement><Subelement Path="5"><StartValue>0</StartValue></Subelement><Subelement Path="6"><StartValue>0</StartValue></Subelement></Member></Section></Sections></Member></Section></Sections></Member><Member Name="Mod_Client" Datatype="Array[1..6] of &quot;Mod_Client_Data&quot;"><Sections><Section Name="None"><Member Name="request" Datatype="Bool"><Subelement Path="1,1"><StartValue>false</StartValue></Subelement><Subelement Path="1,2"><StartValue>false</StartValue></Subelement><Subelement Path="1,3"><StartValue>false</StartValue></Subelement><Subelement Path="1,4"><StartValue>false</StartValue></Subelement><Subelement Path="1,5"><StartValue>false</StartValue></Subelement><Subelement Path="1,6"><StartValue>false</StartValue></Subelement><Subelement Path="2,1"><StartValue>false</StartValue></Subelement><Subelement Path="2,2"><StartValue>false</StartValue></Subelement><Subelement Path="2,3"><StartValue>false</StartValue></Subelement><Subelement Path="2,4"><StartValue>false</StartValue></Subelement><Subelement Path="2,5"><StartValue>false</StartValue></Subelement><Subelement Path="2,6"><StartValue>false</StartValue></Subelement><Subelement Path="3,1"><StartValue>false</StartValue></Subelement><Subelement Path="3,2"><StartValue>false</StartValue></Subelement><Subelement Path="3,3"><StartValue>false</StartValue></Subelement><Subelement Path="3,4"><StartValue>false</StartValue></Subelement><Subelement Path="3,5"><StartValue>false</StartValue></Subelement><Subelement Path="3,6"><StartValue>false</StartValue></Subelement><Subelement Path="4,1"><StartValue>false</StartValue></Subelement><Subelement Path="4,2"><StartValue>false</StartValue></Subelement><Subelement Path="4,3"><StartValue>false</StartValue></Subelement><Subelement Path="4,4"><StartValue>false</StartValue></Subelement><Subelement Path="4,5"><StartValue>false</StartValue></Subelement><Subelement Path="4,6"><StartValue>false</StartValue></Subelement><Subelement Path="5,1"><StartValue>false</StartValue></Subelement><Subelement Path="5,2"><StartValue>false</StartValue></Subelement><Subelement Path="5,3"><StartValue>false</StartValue></Subelement><Subelement Path="5,4"><StartValue>false</StartValue></Subelement><Subelement Path="5,5"><StartValue>false</StartValue></Subelement><Subelement Path="5,6"><StartValue>false</StartValue></Subelement><Subelement Path="6,1"><StartValue>false</StartValue></Subelement><Subelement Path="6,2"><StartValue>false</StartValue></Subelement><Subelement Path="6,3"><StartValue>false</StartValue></Subelement><Subelement Path="6,4"><StartValue>false</StartValue></Subelement><Subelement Path="6,5"><StartValue>false</StartValue></Subelement><Subelement Path="6,6"><StartValue>false</StartValue></Subelement></Member><Member Name="enable" Datatype="Bool"><Subelement Path="1,1"><StartValue>false</StartValue></Subelement><Subelement Path="1,2"><StartValue>false</StartValue></Subelement><Subelement Path="1,3"><StartValue>false</StartValue></Subelement><Subelement Path="1,4"><StartValue>false</StartValue></Subelement><Subelement Path="1,5"><StartValue>false</StartValue></Subelement><Subelement Path="1,6"><StartValue>false</StartValue></Subelement><Subelement Path="2,1"><StartValue>false</StartValue></Subelement><Subelement Path="2,2"><StartValue>false</StartValue></Subelement><Subelement Path="2,3"><StartValue>false</StartValue></Subelement><Subelement Path="2,4"><StartValue>false</StartValue></Subelement><Subelement Path="2,5"><StartValue>false</StartValue></Subelement><Subelement Path="2,6"><StartValue>false</StartValue></Subelement><Subelement Path="3,1"><StartValue>false</StartValue></Subelement><Subelement Path="3,2"><StartValue>false</StartValue></Subelement><Subelement Path="3,3"><StartValue>false</StartValue></Subelement><Subelement Path="3,4"><StartValue>false</StartValue></Subelement><Subelement Path="3,5"><StartValue>false</StartValue></Subelement><Subelement Path="3,6"><StartValue>false</StartValue></Subelement><Subelement Path="4,1"><StartValue>false</StartValue></Subelement><Subelement Path="4,2"><StartValue>false</StartValue></Subelement><Subelement Path="4,3"><StartValue>false</StartValue></Subelement><Subelement Path="4,4"><StartValue>false</StartValue></Subelement><Subelement Path="4,5"><StartValue>false</StartValue></Subelement><Subelement Path="4,6"><StartValue>false</StartValue></Subelement><Subelement Path="5,1"><StartValue>false</StartValue></Subelement><Subelement Path="5,2"><StartValue>false</StartValue></Subelement><Subelement Path="5,3"><StartValue>false</StartValue></Subelement><Subelement Path="5,4"><StartValue>false</StartValue></Subelement><Subelement Path="5,5"><StartValue>false</StartValue></Subelement><Subelement Path="5,6"><StartValue>false</StartValue></Subelement><Subelement Path="6,1"><StartValue>false</StartValue></Subelement><Subelement Path="6,2"><StartValue>false</StartValue></Subelement><Subelement Path="6,3"><StartValue>false</StartValue></Subelement><Subelement Path="6,4"><StartValue>false</StartValue></Subelement><Subelement Path="6,5"><StartValue>false</StartValue></Subelement><Subelement Path="6,6"><StartValue>false</StartValue></Subelement></Member><Member Name="disconnect" Datatype="Bool"><Subelement Path="1,1"><StartValue>false</StartValue></Subelement><Subelement Path="1,2"><StartValue>false</StartValue></Subelement><Subelement Path="1,3"><StartValue>false</StartValue></Subelement><Subelement Path="1,4"><StartValue>false</StartValue></Subelement><Subelement Path="1,5"><StartValue>false</StartValue></Subelement><Subelement Path="1,6"><StartValue>false</StartValue></Subelement><Subelement Path="2,1"><StartValue>false</StartValue></Subelement><Subelement Path="2,2"><StartValue>false</StartValue></Subelement><Subelement Path="2,3"><StartValue>false</StartValue></Subelement><Subelement Path="2,4"><StartValue>false</StartValue></Subelement><Subelement Path="2,5"><StartValue>false</StartValue></Subelement><Subelement Path="2,6"><StartValue>false</StartValue></Subelement><Subelement Path="3,1"><StartValue>false</StartValue></Subelement><Subelement Path="3,2"><StartValue>false</StartValue></Subelement><Subelement Path="3,3"><StartValue>false</StartValue></Subelement><Subelement Path="3,4"><StartValue>false</StartValue></Subelement><Subelement Path="3,5"><StartValue>false</StartValue></Subelement><Subelement Path="3,6"><StartValue>false</StartValue></Subelement><Subelement Path="4,1"><StartValue>false</StartValue></Subelement><Subelement Path="4,2"><StartValue>false</StartValue></Subelement><Subelement Path="4,3"><StartValue>false</StartValue></Subelement><Subelement Path="4,4"><StartValue>false</StartValue></Subelement><Subelement Path="4,5"><StartValue>false</StartValue></Subelement><Subelement Path="4,6"><StartValue>false</StartValue></Subelement><Subelement Path="5,1"><StartValue>false</StartValue></Subelement><Subelement Path="5,2"><StartValue>false</StartValue></Subelement><Subelement Path="5,3"><StartValue>false</StartValue></Subelement><Subelement Path="5,4"><StartValue>false</StartValue></Subelement><Subelement Path="5,5"><StartValue>false</StartValue></Subelement><Subelement Path="5,6"><StartValue>false</StartValue></Subelement><Subelement Path="6,1"><StartValue>false</StartValue></Subelement><Subelement Path="6,2"><StartValue>false</StartValue></Subelement><Subelement Path="6,3"><StartValue>false</StartValue></Subelement><Subelement Path="6,4"><StartValue>false</StartValue></Subelement><Subelement Path="6,5"><StartValue>false</StartValue></Subelement><Subelement Path="6,6"><StartValue>false</StartValue></Subelement></Member><Member Name="done" Datatype="Bool"><Subelement Path="1,1"><StartValue>false</StartValue></Subelement><Subelement Path="1,2"><StartValue>false</StartValue></Subelement><Subelement Path="1,3"><StartValue>false</StartValue></Subelement><Subelement Path="1,4"><StartValue>false</StartValue></Subelement><Subelement Path="1,5"><StartValue>false</StartValue></Subelement><Subelement Path="1,6"><StartValue>false</StartValue></Subelement><Subelement Path="2,1"><StartValue>false</StartValue></Subelement><Subelement Path="2,2"><StartValue>false</StartValue></Subelement><Subelement Path="2,3"><StartValue>false</StartValue></Subelement><Subelement Path="2,4"><StartValue>false</StartValue></Subelement><Subelement Path="2,5"><StartValue>false</StartValue></Subelement><Subelement Path="2,6"><StartValue>false</StartValue></Subelement><Subelement Path="3,1"><StartValue>false</StartValue></Subelement><Subelement Path="3,2"><StartValue>false</StartValue></Subelement><Subelement Path="3,3"><StartValue>false</StartValue></Subelement><Subelement Path="3,4"><StartValue>false</StartValue></Subelement><Subelement Path="3,5"><StartValue>false</StartValue></Subelement><Subelement Path="3,6"><StartValue>false</StartValue></Subelement><Subelement Path="4,1"><StartValue>false</StartValue></Subelement><Subelement Path="4,2"><StartValue>false</StartValue></Subelement><Subelement Path="4,3"><StartValue>false</StartValue></Subelement><Subelement Path="4,4"><StartValue>false</StartValue></Subelement><Subelement Path="4,5"><StartValue>false</StartValue></Subelement><Subelement Path="4,6"><StartValue>false</StartValue></Subelement><Subelement Path="5,1"><StartValue>false</StartValue></Subelement><Subelement Path="5,2"><StartValue>false</StartValue></Subelement><Subelement Path="5,3"><StartValue>false</StartValue></Subelement><Subelement Path="5,4"><StartValue>false</StartValue></Subelement><Subelement Path="5,5"><StartValue>false</StartValue></Subelement><Subelement Path="5,6"><StartValue>false</StartValue></Subelement><Subelement Path="6,1"><StartValue>false</StartValue></Subelement><Subelement Path="6,2"><StartValue>false</StartValue></Subelement><Subelement Path="6,3"><StartValue>false</StartValue></Subelement><Subelement Path="6,4"><StartValue>false</StartValue></Subelement><Subelement Path="6,5"><StartValue>false</StartValue></Subelement><Subelement Path="6,6"><StartValue>false</StartValue></Subelement></Member><Member Name="busy" Datatype="Bool"><Subelement Path="1,1"><StartValue>false</StartValue></Subelement><Subelement Path="1,2"><StartValue>false</StartValue></Subelement><Subelement Path="1,3"><StartValue>false</StartValue></Subelement><Subelement Path="1,4"><StartValue>false</StartValue></Subelement><Subelement Path="1,5"><StartValue>false</StartValue></Subelement><Subelement Path="1,6"><StartValue>false</StartValue></Subelement><Subelement Path="2,1"><StartValue>false</StartValue></Subelement><Subelement Path="2,2"><StartValue>false</StartValue></Subelement><Subelement Path="2,3"><StartValue>false</StartValue></Subelement><Subelement Path="2,4"><StartValue>false</StartValue></Subelement><Subelement Path="2,5"><StartValue>false</StartValue></Subelement><Subelement Path="2,6"><StartValue>false</StartValue></Subelement><Subelement Path="3,1"><StartValue>false</StartValue></Subelement><Subelement Path="3,2"><StartValue>false</StartValue></Subelement><Subelement Path="3,3"><StartValue>false</StartValue></Subelement><Subelement Path="3,4"><StartValue>false</StartValue></Subelement><Subelement Path="3,5"><StartValue>false</StartValue></Subelement><Subelement Path="3,6"><StartValue>false</StartValue></Subelement><Subelement Path="4,1"><StartValue>false</StartValue></Subelement><Subelement Path="4,2"><StartValue>false</StartValue></Subelement><Subelement Path="4,3"><StartValue>false</StartValue></Subelement><Subelement Path="4,4"><StartValue>false</StartValue></Subelement><Subelement Path="4,5"><StartValue>false</StartValue></Subelement><Subelement Path="4,6"><StartValue>false</StartValue></Subelement><Subelement Path="5,1"><StartValue>false</StartValue></Subelement><Subelement Path="5,2"><StartValue>false</StartValue></Subelement><Subelement Path="5,3"><StartValue>false</StartValue></Subelement><Subelement Path="5,4"><StartValue>false</StartValue></Subelement><Subelement Path="5,5"><StartValue>false</StartValue></Subelement><Subelement Path="5,6"><StartValue>false</StartValue></Subelement><Subelement Path="6,1"><StartValue>false</StartValue></Subelement><Subelement Path="6,2"><StartValue>false</StartValue></Subelement><Subelement Path="6,3"><StartValue>false</StartValue></Subelement><Subelement Path="6,4"><StartValue>false</StartValue></Subelement><Subelement Path="6,5"><StartValue>false</StartValue></Subelement><Subelement Path="6,6"><StartValue>false</StartValue></Subelement></Member><Member Name="error" Datatype="Bool"><Subelement Path="1,1"><StartValue>false</StartValue></Subelement><Subelement Path="1,2"><StartValue>false</StartValue></Subelement><Subelement Path="1,3"><StartValue>false</StartValue></Subelement><Subelement Path="1,4"><StartValue>false</StartValue></Subelement><Subelement Path="1,5"><StartValue>false</StartValue></Subelement><Subelement Path="1,6"><StartValue>false</StartValue></Subelement><Subelement Path="2,1"><StartValue>false</StartValue></Subelement><Subelement Path="2,2"><StartValue>false</StartValue></Subelement><Subelement Path="2,3"><StartValue>false</StartValue></Subelement><Subelement Path="2,4"><StartValue>false</StartValue></Subelement><Subelement Path="2,5"><StartValue>false</StartValue></Subelement><Subelement Path="2,6"><StartValue>false</StartValue></Subelement><Subelement Path="3,1"><StartValue>false</StartValue></Subelement><Subelement Path="3,2"><StartValue>false</StartValue></Subelement><Subelement Path="3,3"><StartValue>false</StartValue></Subelement><Subelement Path="3,4"><StartValue>false</StartValue></Subelement><Subelement Path="3,5"><StartValue>false</StartValue></Subelement><Subelement Path="3,6"><StartValue>false</StartValue></Subelement><Subelement Path="4,1"><StartValue>false</StartValue></Subelement><Subelement Path="4,2"><StartValue>false</StartValue></Subelement><Subelement Path="4,3"><StartValue>false</StartValue></Subelement><Subelement Path="4,4"><StartValue>false</StartValue></Subelement><Subelement Path="4,5"><StartValue>false</StartValue></Subelement><Subelement Path="4,6"><StartValue>false</StartValue></Subelement><Subelement Path="5,1"><StartValue>false</StartValue></Subelement><Subelement Path="5,2"><StartValue>false</StartValue></Subelement><Subelement Path="5,3"><StartValue>false</StartValue></Subelement><Subelement Path="5,4"><StartValue>false</StartValue></Subelement><Subelement Path="5,5"><StartValue>false</StartValue></Subelement><Subelement Path="5,6"><StartValue>false</StartValue></Subelement><Subelement Path="6,1"><StartValue>false</StartValue></Subelement><Subelement Path="6,2"><StartValue>false</StartValue></Subelement><Subelement Path="6,3"><StartValue>false</StartValue></Subelement><Subelement Path="6,4"><StartValue>false</StartValue></Subelement><Subelement Path="6,5"><StartValue>false</StartValue></Subelement><Subelement Path="6,6"><StartValue>false</StartValue></Subelement></Member><Member Name="status" Datatype="Word"><Subelement Path="1,1"><StartValue>16#0</StartValue></Subelement><Subelement Path="1,2"><StartValue>16#0</StartValue></Subelement><Subelement Path="1,3"><StartValue>16#0</StartValue></Subelement><Subelement Path="1,4"><StartValue>16#0</StartValue></Subelement><Subelement Path="1,5"><StartValue>16#0</StartValue></Subelement><Subelement Path="1,6"><StartValue>16#0</StartValue></Subelement><Subelement Path="2,1"><StartValue>16#0</StartValue></Subelement><Subelement Path="2,2"><StartValue>16#0</StartValue></Subelement><Subelement Path="2,3"><StartValue>16#0</StartValue></Subelement><Subelement Path="2,4"><StartValue>16#0</StartValue></Subelement><Subelement Path="2,5"><StartValue>16#0</StartValue></Subelement><Subelement Path="2,6"><StartValue>16#0</StartValue></Subelement><Subelement Path="3,1"><StartValue>16#0</StartValue></Subelement><Subelement Path="3,2"><StartValue>16#0</StartValue></Subelement><Subelement Path="3,3"><StartValue>16#0</StartValue></Subelement><Subelement Path="3,4"><StartValue>16#0</StartValue></Subelement><Subelement Path="3,5"><StartValue>16#0</StartValue></Subelement><Subelement Path="3,6"><StartValue>16#0</StartValue></Subelement><Subelement Path="4,1"><StartValue>16#0</StartValue></Subelement><Subelement Path="4,2"><StartValue>16#0</StartValue></Subelement><Subelement Path="4,3"><StartValue>16#0</StartValue></Subelement><Subelement Path="4,4"><StartValue>16#0</StartValue></Subelement><Subelement Path="4,5"><StartValue>16#0</StartValue></Subelement><Subelement Path="4,6"><StartValue>16#0</StartValue></Subelement><Subelement Path="5,1"><StartValue>16#0</StartValue></Subelement><Subelement Path="5,2"><StartValue>16#0</StartValue></Subelement><Subelement Path="5,3"><StartValue>16#0</StartValue></Subelement><Subelement Path="5,4"><StartValue>16#0</StartValue></Subelement><Subelement Path="5,5"><StartValue>16#0</StartValue></Subelement><Subelement Path="5,6"><StartValue>16#0</StartValue></Subelement><Subelement Path="6,1"><StartValue>16#0</StartValue></Subelement><Subelement Path="6,2"><StartValue>16#0</StartValue></Subelement><Subelement Path="6,3"><StartValue>16#0</StartValue></Subelement><Subelement Path="6,4"><StartValue>16#0</StartValue></Subelement><Subelement Path="6,5"><StartValue>16#0</StartValue></Subelement><Subelement Path="6,6"><StartValue>16#0</StartValue></Subelement></Member><Member Name="statusSave" Datatype="Word"><Subelement Path="1,1"><StartValue>16#0</StartValue></Subelement><Subelement Path="1,2"><StartValue>16#0</StartValue></Subelement><Subelement Path="1,3"><StartValue>16#0</StartValue></Subelement><Subelement Path="1,4"><StartValue>16#0</StartValue></Subelement><Subelement Path="1,5"><StartValue>16#0</StartValue></Subelement><Subelement Path="1,6"><StartValue>16#0</StartValue></Subelement><Subelement Path="2,1"><StartValue>16#0</StartValue></Subelement><Subelement Path="2,2"><StartValue>16#0</StartValue></Subelement><Subelement Path="2,3"><StartValue>16#0</StartValue></Subelement><Subelement Path="2,4"><StartValue>16#0</StartValue></Subelement><Subelement Path="2,5"><StartValue>16#0</StartValue></Subelement><Subelement Path="2,6"><StartValue>16#0</StartValue></Subelement><Subelement Path="3,1"><StartValue>16#0</StartValue></Subelement><Subelement Path="3,2"><StartValue>16#0</StartValue></Subelement><Subelement Path="3,3"><StartValue>16#0</StartValue></Subelement><Subelement Path="3,4"><StartValue>16#0</StartValue></Subelement><Subelement Path="3,5"><StartValue>16#0</StartValue></Subelement><Subelement Path="3,6"><StartValue>16#0</StartValue></Subelement><Subelement Path="4,1"><StartValue>16#0</StartValue></Subelement><Subelement Path="4,2"><StartValue>16#0</StartValue></Subelement><Subelement Path="4,3"><StartValue>16#0</StartValue></Subelement><Subelement Path="4,4"><StartValue>16#0</StartValue></Subelement><Subelement Path="4,5"><StartValue>16#0</StartValue></Subelement><Subelement Path="4,6"><StartValue>16#0</StartValue></Subelement><Subelement Path="5,1"><StartValue>16#0</StartValue></Subelement><Subelement Path="5,2"><StartValue>16#0</StartValue></Subelement><Subelement Path="5,3"><StartValue>16#0</StartValue></Subelement><Subelement Path="5,4"><StartValue>16#0</StartValue></Subelement><Subelement Path="5,5"><StartValue>16#0</StartValue></Subelement><Subelement Path="5,6"><StartValue>16#0</StartValue></Subelement><Subelement Path="6,1"><StartValue>16#0</StartValue></Subelement><Subelement Path="6,2"><StartValue>16#0</StartValue></Subelement><Subelement Path="6,3"><StartValue>16#0</StartValue></Subelement><Subelement Path="6,4"><StartValue>16#0</StartValue></Subelement><Subelement Path="6,5"><StartValue>16#0</StartValue></Subelement><Subelement Path="6,6"><StartValue>16#0</StartValue></Subelement></Member><Member Name="modbusMode" Datatype="USInt"><Subelement Path="1,1"><StartValue>1</StartValue></Subelement><Subelement Path="1,2"><StartValue>0</StartValue></Subelement><Subelement Path="1,3"><StartValue>1</StartValue></Subelement><Subelement Path="1,4"><StartValue>0</StartValue></Subelement><Subelement Path="1,5"><StartValue>0</StartValue></Subelement><Subelement Path="1,6"><StartValue>1</StartValue></Subelement><Subelement Path="2,1"><StartValue>1</StartValue></Subelement><Subelement Path="2,2"><StartValue>0</StartValue></Subelement><Subelement Path="2,3"><StartValue>1</StartValue></Subelement><Subelement Path="2,4"><StartValue>0</StartValue></Subelement><Subelement Path="2,5"><StartValue>0</StartValue></Subelement><Subelement Path="2,6"><StartValue>1</StartValue></Subelement><Subelement Path="3,1"><StartValue>1</StartValue></Subelement><Subelement Path="3,2"><StartValue>0</StartValue></Subelement><Subelement Path="3,3"><StartValue>1</StartValue></Subelement><Subelement Path="3,4"><StartValue>0</StartValue></Subelement><Subelement Path="3,5"><StartValue>0</StartValue></Subelement><Subelement Path="3,6"><StartValue>1</StartValue></Subelement><Subelement Path="4,1"><StartValue>1</StartValue></Subelement><Subelement Path="4,2"><StartValue>0</StartValue></Subelement><Subelement Path="4,3"><StartValue>1</StartValue></Subelement><Subelement Path="4,4"><StartValue>0</StartValue></Subelement><Subelement Path="4,5"><StartValue>0</StartValue></Subelement><Subelement Path="4,6"><StartValue>1</StartValue></Subelement><Subelement Path="5,1"><StartValue>1</StartValue></Subelement><Subelement Path="5,2"><StartValue>0</StartValue></Subelement><Subelement Path="5,3"><StartValue>1</StartValue></Subelement><Subelement Path="5,4"><StartValue>0</StartValue></Subelement><Subelement Path="5,5"><StartValue>0</StartValue></Subelement><Subelement Path="5,6"><StartValue>1</StartValue></Subelement><Subelement Path="6,1"><StartValue>1</StartValue></Subelement><Subelement Path="6,2"><StartValue>0</StartValue></Subelement><Subelement Path="6,3"><StartValue>1</StartValue></Subelement><Subelement Path="6,4"><StartValue>0</StartValue></Subelement><Subelement Path="6,5"><StartValue>0</StartValue></Subelement><Subelement Path="6,6"><StartValue>1</StartValue></Subelement></Member><Member Name="modbusDataAddress" Datatype="UDInt"><Subelement Path="1,1"><StartValue>40908</StartValue></Subelement><Subelement Path="1,2"><StartValue>40001</StartValue></Subelement><Subelement Path="1,3"><StartValue>40302</StartValue></Subelement><Subelement Path="1,4"><StartValue>0</StartValue></Subelement><Subelement Path="1,5"><StartValue>1</StartValue></Subelement><Subelement Path="1,6"><StartValue>0</StartValue></Subelement><Subelement Path="2,1"><StartValue>40908</StartValue></Subelement><Subelement Path="2,2"><StartValue>40001</StartValue></Subelement><Subelement Path="2,3"><StartValue>40302</StartValue></Subelement><Subelement Path="2,4"><StartValue>0</StartValue></Subelement><Subelement Path="2,5"><StartValue>1</StartValue></Subelement><Subelement Path="2,6"><StartValue>0</StartValue></Subelement><Subelement Path="3,1"><StartValue>40908</StartValue></Subelement><Subelement Path="3,2"><StartValue>40001</StartValue></Subelement><Subelement Path="3,3"><StartValue>40302</StartValue></Subelement><Subelement Path="3,4"><StartValue>0</StartValue></Subelement><Subelement Path="3,5"><StartValue>1</StartValue></Subelement><Subelement Path="3,6"><StartValue>0</StartValue></Subelement><Subelement Path="4,1"><StartValue>40908</StartValue></Subelement><Subelement Path="4,2"><StartValue>40001</StartValue></Subelement><Subelement Path="4,3"><StartValue>40302</StartValue></Subelement><Subelement Path="4,4"><StartValue>0</StartValue></Subelement><Subelement Path="4,5"><StartValue>1</StartValue></Subelement><Subelement Path="4,6"><StartValue>0</StartValue></Subelement><Subelement Path="5,1"><StartValue>40908</StartValue></Subelement><Subelement Path="5,2"><StartValue>40001</StartValue></Subelement><Subelement Path="5,3"><StartValue>40302</StartValue></Subelement><Subelement Path="5,4"><StartValue>0</StartValue></Subelement><Subelement Path="5,5"><StartValue>1</StartValue></Subelement><Subelement Path="5,6"><StartValue>0</StartValue></Subelement><Subelement Path="6,1"><StartValue>40908</StartValue></Subelement><Subelement Path="6,2"><StartValue>40001</StartValue></Subelement><Subelement Path="6,3"><StartValue>40302</StartValue></Subelement><Subelement Path="6,4"><StartValue>0</StartValue></Subelement><Subelement Path="6,5"><StartValue>1</StartValue></Subelement><Subelement Path="6,6"><StartValue>0</StartValue></Subelement></Member><Member Name="modbusDataLen" Datatype="UInt"><Subelement Path="1,1"><StartValue>1</StartValue></Subelement><Subelement Path="1,2"><StartValue>6</StartValue></Subelement><Subelement Path="1,3"><StartValue>1</StartValue></Subelement><Subelement Path="1,4"><StartValue>0</StartValue></Subelement><Subelement Path="1,5"><StartValue>32</StartValue></Subelement><Subelement Path="1,6"><StartValue>1</StartValue></Subelement><Subelement Path="2,1"><StartValue>1</StartValue></Subelement><Subelement Path="2,2"><StartValue>6</StartValue></Subelement><Subelement Path="2,3"><StartValue>1</StartValue></Subelement><Subelement Path="2,4"><StartValue>0</StartValue></Subelement><Subelement Path="2,5"><StartValue>32</StartValue></Subelement><Subelement Path="2,6"><StartValue>1</StartValue></Subelement><Subelement Path="3,1"><StartValue>1</StartValue></Subelement><Subelement Path="3,2"><StartValue>6</StartValue></Subelement><Subelement Path="3,3"><StartValue>1</StartValue></Subelement><Subelement Path="3,4"><StartValue>0</StartValue></Subelement><Subelement Path="3,5"><StartValue>32</StartValue></Subelement><Subelement Path="3,6"><StartValue>1</StartValue></Subelement><Subelement Path="4,1"><StartValue>1</StartValue></Subelement><Subelement Path="4,2"><StartValue>6</StartValue></Subelement><Subelement Path="4,3"><StartValue>1</StartValue></Subelement><Subelement Path="4,4"><StartValue>0</StartValue></Subelement><Subelement Path="4,5"><StartValue>32</StartValue></Subelement><Subelement Path="4,6"><StartValue>1</StartValue></Subelement><Subelement Path="5,1"><StartValue>1</StartValue></Subelement><Subelement Path="5,2"><StartValue>6</StartValue></Subelement><Subelement Path="5,3"><StartValue>1</StartValue></Subelement><Subelement Path="5,4"><StartValue>0</StartValue></Subelement><Subelement Path="5,5"><StartValue>32</StartValue></Subelement><Subelement Path="5,6"><StartValue>1</StartValue></Subelement><Subelement Path="6,1"><StartValue>1</StartValue></Subelement><Subelement Path="6,2"><StartValue>6</StartValue></Subelement><Subelement Path="6,3"><StartValue>1</StartValue></Subelement><Subelement Path="6,4"><StartValue>0</StartValue></Subelement><Subelement Path="6,5"><StartValue>32</StartValue></Subelement><Subelement Path="6,6"><StartValue>1</StartValue></Subelement></Member></Section></Sections></Member></Section></Sections></Member>
    <Member Name="TCP_Data_CHECK_SCALE_1" Datatype="&quot;Mod_TCP_Data&quot;" Remanence="Retain" Accessibility="Public"><AttributeList><BooleanAttribute Name="ExternalAccessible" SystemDefined="true">true</BooleanAttribute><BooleanAttribute Name="ExternalVisible" SystemDefined="true">true</BooleanAttribute><BooleanAttribute Name="ExternalWritable" SystemDefined="true">true</BooleanAttribute><BooleanAttribute Name="SetPoint" SystemDefined="true">true</BooleanAttribute></AttributeList><Sections><Section Name="None"><Member Name="Mod_TCP_Connect" Datatype="&quot;Mod_Connect_Data&quot;"><Sections><Section Name="None"><Member Name="connectParamClient" Datatype="TCON_IP_v4" Version="1.0"><Sections><Section Name="None"><Member Name="InterfaceId" Datatype="HW_ANY"><StartValue>64</StartValue></Member><Member Name="ID" Datatype="CONN_OUC"><StartValue>21</StartValue></Member><Member Name="ConnectionType" Datatype="Byte"><StartValue>16#0B</StartValue></Member><Member Name="ActiveEstablished" Datatype="Bool"><StartValue>true</StartValue></Member><Member Name="RemoteAddress" Datatype="IP_V4" Version="1.0"><Sections><Section Name="None"><Member Name="ADDR" Datatype="Array[1..4] of Byte"><Subelement Path="1"><StartValue>192</StartValue></Subelement><Subelement Path="2"><StartValue>168</StartValue></Subelement><Subelement Path="3"><StartValue>0</StartValue></Subelement><Subelement Path="4"><StartValue>41</StartValue></Subelement></Member></Section></Sections></Member><Member Name="RemotePort" Datatype="UInt"><StartValue>502</StartValue></Member><Member Name="LocalPort" Datatype="UInt"><StartValue>0</StartValue></Member></Section></Sections></Member></Section></Sections></Member><Member Name="Mod_Client" Datatype="Array[1..6] of &quot;Mod_Client_Data&quot;"><Sections><Section Name="None"><Member Name="request" Datatype="Bool"><Subelement Path="1"><StartValue>false</StartValue></Subelement><Subelement Path="2"><StartValue>false</StartValue></Subelement><Subelement Path="3"><StartValue>false</StartValue></Subelement><Subelement Path="4"><StartValue>false</StartValue></Subelement><Subelement Path="5"><StartValue>false</StartValue></Subelement><Subelement Path="6"><StartValue>false</StartValue></Subelement></Member><Member Name="enable" Datatype="Bool"><Subelement Path="1"><StartValue>false</StartValue></Subelement><Subelement Path="2"><StartValue>false</StartValue></Subelement><Subelement Path="3"><StartValue>false</StartValue></Subelement><Subelement Path="4"><StartValue>false</StartValue></Subelement><Subelement Path="5"><StartValue>false</StartValue></Subelement><Subelement Path="6"><StartValue>false</StartValue></Subelement></Member><Member Name="disconnect" Datatype="Bool"><Subelement Path="1"><StartValue>false</StartValue></Subelement><Subelement Path="2"><StartValue>false</StartValue></Subelement><Subelement Path="3"><StartValue>false</StartValue></Subelement><Subelement Path="4"><StartValue>false</StartValue></Subelement><Subelement Path="5"><StartValue>false</StartValue></Subelement><Subelement Path="6"><StartValue>false</StartValue></Subelement></Member><Member Name="done" Datatype="Bool"><Subelement Path="1"><StartValue>false</StartValue></Subelement><Subelement Path="2"><StartValue>false</StartValue></Subelement><Subelement Path="3"><StartValue>false</StartValue></Subelement><Subelement Path="4"><StartValue>false</StartValue></Subelement><Subelement Path="5"><StartValue>false</StartValue></Subelement><Subelement Path="6"><StartValue>false</StartValue></Subelement></Member><Member Name="busy" Datatype="Bool"><Subelement Path="1"><StartValue>false</StartValue></Subelement><Subelement Path="2"><StartValue>false</StartValue></Subelement><Subelement Path="3"><StartValue>false</StartValue></Subelement><Subelement Path="4"><StartValue>false</StartValue></Subelement><Subelement Path="5"><StartValue>false</StartValue></Subelement><Subelement Path="6"><StartValue>false</StartValue></Subelement></Member><Member Name="error" Datatype="Bool"><Subelement Path="1"><StartValue>false</StartValue></Subelement><Subelement Path="2"><StartValue>false</StartValue></Subelement><Subelement Path="3"><StartValue>false</StartValue></Subelement><Subelement Path="4"><StartValue>false</StartValue></Subelement><Subelement Path="5"><StartValue>false</StartValue></Subelement><Subelement Path="6"><StartValue>false</StartValue></Subelement></Member><Member Name="status" Datatype="Word"><Subelement Path="1"><StartValue>16#0</StartValue></Subelement><Subelement Path="2"><StartValue>16#0</StartValue></Subelement><Subelement Path="3"><StartValue>16#0</StartValue></Subelement><Subelement Path="4"><StartValue>16#0</StartValue></Subelement><Subelement Path="5"><StartValue>16#0</StartValue></Subelement><Subelement Path="6"><StartValue>16#0</StartValue></Subelement></Member><Member Name="statusSave" Datatype="Word"><Subelement Path="1"><StartValue>16#0</StartValue></Subelement><Subelement Path="2"><StartValue>16#0</StartValue></Subelement><Subelement Path="3"><StartValue>16#0</StartValue></Subelement><Subelement Path="4"><StartValue>16#0</StartValue></Subelement><Subelement Path="5"><StartValue>16#0</StartValue></Subelement><Subelement Path="6"><StartValue>16#0</StartValue></Subelement></Member><Member Name="modbusMode" Datatype="USInt"><Subelement Path="1"><StartValue>1</StartValue></Subelement><Subelement Path="2"><StartValue>0</StartValue></Subelement><Subelement Path="3"><StartValue>1</StartValue></Subelement><Subelement Path="4"><StartValue>0</StartValue></Subelement><Subelement Path="5"><StartValue>0</StartValue></Subelement><Subelement Path="6"><StartValue>1</StartValue></Subelement></Member><Member Name="modbusDataAddress" Datatype="UDInt"><Subelement Path="1"><StartValue>40908</StartValue></Subelement><Subelement Path="2"><StartValue>40011</StartValue></Subelement><Subelement Path="3"><StartValue>40302</StartValue></Subelement><Subelement Path="4"><StartValue>0</StartValue></Subelement><Subelement Path="5"><StartValue>1</StartValue></Subelement><Subelement Path="6"><StartValue>0</StartValue></Subelement></Member><Member Name="modbusDataLen" Datatype="UInt"><Subelement Path="1"><StartValue>1</StartValue></Subelement><Subelement Path="2"><StartValue>10</StartValue></Subelement><Subelement Path="3"><StartValue>1</StartValue></Subelement><Subelement Path="4"><StartValue>0</StartValue></Subelement><Subelement Path="5"><StartValue>32</StartValue></Subelement><Subelement Path="6"><StartValue>1</StartValue></Subelement></Member></Section></Sections></Member></Section></Sections></Member>
    <Member Name="TCP_Data_CORRECTION_SCALE" Datatype="&quot;Mod_TCP_Data&quot;" Remanence="Retain" Accessibility="Public"><AttributeList><BooleanAttribute Name="ExternalAccessible" SystemDefined="true">true</BooleanAttribute><BooleanAttribute Name="ExternalVisible" SystemDefined="true">true</BooleanAttribute><BooleanAttribute Name="ExternalWritable" SystemDefined="true">true</BooleanAttribute><BooleanAttribute Name="SetPoint" SystemDefined="true">true</BooleanAttribute></AttributeList><Sections><Section Name="None"><Member Name="Mod_TCP_Connect" Datatype="&quot;Mod_Connect_Data&quot;"><Sections><Section Name="None"><Member Name="connectParamClient" Datatype="TCON_IP_v4" Version="1.0"><Sections><Section Name="None"><Member Name="InterfaceId" Datatype="HW_ANY"><StartValue>64</StartValue></Member><Member Name="ID" Datatype="CONN_OUC"><StartValue>41</StartValue></Member><Member Name="ConnectionType" Datatype="Byte"><StartValue>16#0B</StartValue></Member><Member Name="ActiveEstablished" Datatype="Bool"><StartValue>TRUE</StartValue></Member><Member Name="RemoteAddress" Datatype="IP_V4" Version="1.0"><Sections><Section Name="None"><Member Name="ADDR" Datatype="Array[1..4] of Byte"><Subelement Path="1"><StartValue>192</StartValue></Subelement><Subelement Path="2"><StartValue>168</StartValue></Subelement><Subelement Path="3"><StartValue>0</StartValue></Subelement><Subelement Path="4"><StartValue>41</StartValue></Subelement></Member></Section></Sections></Member><Member Name="RemotePort" Datatype="UInt"><StartValue>502</StartValue></Member><Member Name="LocalPort" Datatype="UInt" /></Section></Sections></Member></Section></Sections></Member><Member Name="Mod_Client" Datatype="Array[1..6] of &quot;Mod_Client_Data&quot;"><Sections><Section Name="None"><Member Name="request" Datatype="Bool" /><Member Name="enable" Datatype="Bool" /><Member Name="disconnect" Datatype="Bool" /><Member Name="done" Datatype="Bool" /><Member Name="busy" Datatype="Bool" /><Member Name="error" Datatype="Bool" /><Member Name="status" Datatype="Word" /><Member Name="statusSave" Datatype="Word" /><Member Name="modbusMode" Datatype="USInt" /><Member Name="modbusDataAddress" Datatype="UDInt" /><Member Name="modbusDataLen" Datatype="UInt" /></Section></Sections></Member></Section></Sections></Member>
  </Section>
</Sections></Interface>
      <IsOnlyStoredInLoadMemory>false</IsOnlyStoredInLoadMemory>
      <IsWriteProtectedInAS>false</IsWriteProtectedInAS>
      <MemoryLayout>Standard</MemoryLayout>
      <Name>MOD_TCP_SETUP_DB</Name>
      <Number>100</Number>
      <ProgrammingLanguage>DB</ProgrammingLanguage>
    </AttributeList>
    <ObjectList>
      <MultilingualText ID="1" CompositionName="Comment">
        <ObjectList>
          <MultilingualTextItem ID="2" CompositionName="Items">
            <AttributeList>
              <Culture>en-US</Culture>
              <Text />
            </AttributeList>
          </MultilingualTextItem>
        </ObjectList>
      </MultilingualText>
      <MultilingualText ID="3" CompositionName="Title">
        <ObjectList>
          <MultilingualTextItem ID="4" CompositionName="Items">
            <AttributeList>
              <Culture>en-US</Culture>
              <Text />
            </AttributeList>
          </MultilingualTextItem>
        </ObjectList>
      </MultilingualText>
    </ObjectList>
  </SW.Blocks.GlobalDB>
</Document>